django_shift_work/__init__.py
django_shift_work/apps.py
django_shift_work/middlewares.py
django_shift_work/models.py
django_shift_work/urls.py
django_shift_work/views.py
django_shift_work/static/css/django_shift_work.css
django_shift_work/static/js/django_shift_work.js
django_shift_work/templates/django_shift_work/base.html
django_shift_work-0.1.1.dist-info/DESCRIPTION.rst
django_shift_work-0.1.1.dist-info/METADATA
django_shift_work-0.1.1.dist-info/RECORD
django_shift_work-0.1.1.dist-info/WHEEL
django_shift_work-0.1.1.dist-info/metadata.json
django_shift_work-0.1.1.dist-info/top_level.txt
