Metadata-Version: 2.0
Name: django-shift-work
Version: 0.1.1
Summary: Middleware to check what shift is currently active
Home-page: https://github.com/reyvel/django-shift-work
Author: Reyza Velosa
Author-email: reyza@reyvel.id
License: MIT
Keywords: django-shift-work
Platform: UNKNOWN
Classifier: Development Status :: 3 - Alpha
Classifier: Framework :: Django :: 2.0
Classifier: Intended Audience :: Developers
Classifier: License :: OSI Approved :: BSD License
Classifier: Natural Language :: English
Classifier: Programming Language :: Python :: 3.6
